clique/__init__.py
clique/clique.py
clique_ml-0.0.11.dist-info/METADATA
clique_ml-0.0.11.dist-info/WHEEL
clique_ml-0.0.11.dist-info/top_level.txt
clique_ml-0.0.11.dist-info/RECORD
