Metadata-Version: 2.4
Name: clique-ml
Version: 0.0.11
Summary: A selective ensemble for predictive models that tests new additions to prevent downgrades in performance.
Project-URL: Source, https://github.com/whitgroves/clique-ml
Keywords: selective,ensemble,tensorflow,maching learning,cuda
Requires-Python: >=3.10
Requires-Dist: joblib>=1.4.2
Requires-Dist: psutil>=6.1.0
Requires-Dist: pandas>=2.2.2
Requires-Dist: numpy>=1.26.4
Requires-Dist: scikit-learn>=1.5.2
Requires-Dist: typing_extensions>=4.12.2
Requires-Dist: tensorflow>=2.18.0
